MANIFEST.in
README.rst
setup.py
pycontract/__init__.py
pycontract/contract.py
pycontract/exceptions.py
pycontract/fields.py
pycontract/processors.py
pycontract/validators.py
pycontract.egg-info/PKG-INFO
pycontract.egg-info/SOURCES.txt
pycontract.egg-info/dependency_links.txt
pycontract.egg-info/requires.txt
pycontract.egg-info/top_level.txt
pycontract/tests/__init__.py
pycontract/tests/dummycontracts.py
pycontract/tests/test_datacontract.py
pycontract/tests/test_datafield.py
pycontract/tests/test_processors.py