Metadata-Version: 1.0
Name: pycontract
Version: 0.1.3
Summary: A data contracts system for python loosly modeled after django forms.
Home-page: https://github.com/bigjason/pycontract
Author: Jason Webb
Author-email: bigjasonwebb@gmail.com
License: MIT
Platform: UNKNOWN
Classifier: Development Status :: 3 - Alpha
Classifier: Operating System :: OS Independent
Classifier: Programming Language :: Python
Classifier: License :: OSI Approved :: MIT License
Classifier: Intended Audience :: Developers
Classifier: Programming Language :: Python :: 2.7
